{"TotalTicks":463,"Players":[{"Placement":1,"Seed":16480,"Score":62,"Id":"cf352a06-7442-4d00-b027-6b238955def5","Nickname":"T~T_k3nsl3rB","MatchPoints":8},{"Placement":3,"Seed":17228,"Score":28,"Id":"f49853d8-6b83-464f-8cd1-e875d5a85fbc","Nickname":"T~T_k3nsl3rB","MatchPoints":4},{"Placement":2,"Seed":3807,"Score":28,"Id":"7cfd0500-4242-4d2d-9a5a-d1afe73babd7","Nickname":"T~T_k3nsl3rB","MatchPoints":6},{"Placement":4,"Seed":28334,"Score":9,"Id":"dde87c3c-9db2-4bb8-af7c-36fde8512ab0","Nickname":"T~T_k3nsl3rB","MatchPoints":2}],"WorldSeeds":[46723],"WinningBot":{"Id":"cf352a06-7442-4d00-b027-6b238955def5","Size":90,"Speed":3,"GameObjectType":1,"CurrentHeading":32,"Position":{"X":391,"Y":183}}}