{"TotalTicks":470,"Players":[{"Placement":1,"Seed":7284,"Score":76,"Id":"d1a65816-1143-43c5-900c-038fa39b67b6","Nickname":"T~T_k3nsl3rB","MatchPoints":8},{"Placement":2,"Seed":6545,"Score":44,"Id":"a3eb8010-3492-4cb2-ac7e-4a3195eb7081","Nickname":"T~T_k3nsl3rB","MatchPoints":6},{"Placement":3,"Seed":17101,"Score":38,"Id":"53e86593-7a72-4bfd-851b-cced2aa80630","Nickname":"T~T_k3nsl3rB","MatchPoints":4},{"Placement":4,"Seed":15308,"Score":15,"Id":"e44026c3-88df-4897-9cf8-379da35db6e6","Nickname":"T~T_k3nsl3rB","MatchPoints":2}],"WorldSeeds":[22058],"WinningBot":{"Id":"d1a65816-1143-43c5-900c-038fa39b67b6","Size":21,"Speed":10,"GameObjectType":1,"CurrentHeading":97,"Position":{"X":88,"Y":-600}}}